lunchable_splitlunch/__about__.py
lunchable_splitlunch/__init__.py
lunchable_splitlunch/_config.py
lunchable_splitlunch/cli.py
lunchable_splitlunch/exceptions.py
lunchable_splitlunch/lunchmoney_splitwise.py
lunchable_splitlunch/models.py
lunchable_splitlunch/py.typed
lunchable_splitlunch-1.0.3.dist-info/METADATA
lunchable_splitlunch-1.0.3.dist-info/WHEEL
lunchable_splitlunch-1.0.3.dist-info/entry_points.txt
lunchable_splitlunch-1.0.3.dist-info/licenses/LICENSE
lunchable_splitlunch-1.0.3.dist-info/RECORD
