Metadata-Version: 2.1
Name: lunchable-splitlunch
Version: 1.0.3
Summary: LunchMoney + Splitwise Integration
Project-URL: Documentation, https://juftin.github.io/lunchable-splitlunch
Project-URL: Issues, https://github.com/juftin/lunchable-splitlunch/issues
Project-URL: Source, https://github.com/juftin/lunchable-splitlunch
Author-email: Justin Flannery <juftin@juftin.com>
License-Expression: MIT
License-File: LICENSE
Classifier: Development Status :: 5 - Production/Stable
Classifier: Operating System :: OS Independent
Classifier: Programming Language :: Python
Classifier: Programming Language :: Python :: 3.8
Classifier: Programming Language :: Python :: 3.9
Classifier: Programming Language :: Python :: 3.10
Classifier: Programming Language :: Python :: 3.11
Classifier: Programming Language :: Python :: 3.12
Classifier: Programming Language :: Python :: Implementation :: CPython
Classifier: Programming Language :: Python :: Implementation :: PyPy
Requires-Python: >=3.8
Requires-Dist: click
Requires-Dist: lunchable>=1.2.1
Requires-Dist: python-dateutil
Requires-Dist: rich
Requires-Dist: splitwise<3.0.0,>=2.3.0
